pseudorandom/__init__.py
pseudorandom/_constraint.py
pseudorandom/_enforce.py
pseudorandom/_exceptions.py
python_pseudorandom-0.3.2.dist-info/COPYING
python_pseudorandom-0.3.2.dist-info/WHEEL
python_pseudorandom-0.3.2.dist-info/METADATA
python_pseudorandom-0.3.2.dist-info/RECORD
