Metadata-Version: 2.1
Name: python-pseudorandom
Version: 0.3.2
Summary: This file is part of pseudorandom.
Keywords: pseudorandomization,datamatrix,opensesame,experimental design
Author-email: Sebastiaan Mathôt <s.mathot@cogsci.nl>
Requires-Python: >=3.7
Requires-Dist: datamatrix
Project-URL: Documentation, https://github.com/open-cogsci/pseudorandom
Project-URL: Source, https://github.com/open-cogsci/pseudorandom
